rpi_mates/__init__.py
rpi_mates/controller.py
rpi_mates_controller-1.0.3.dist-info/LICENSE
rpi_mates_controller-1.0.3.dist-info/METADATA
rpi_mates_controller-1.0.3.dist-info/WHEEL
rpi_mates_controller-1.0.3.dist-info/top_level.txt
rpi_mates_controller-1.0.3.dist-info/RECORD
