Metadata-Version: 2.1
Name: rpi-mates-controller
Version: 1.0.3
Summary: A Python Library developed to be used with Mates Studio Commander or Architect Environment and BBM modules connected to a Raspberry Pi using BBM Pi Adaptor or with similar connections
Home-page: https://github.com/BreadBoardMates/RPi-Python-Mates-Controller
Author: Breadboard Mates
Author-email: developers@breadboardmates.com
Project-URL: Bug Tracker, https://github.com/BreadBoardMates/RPi-Python-Mates-Controller/issues
Classifier: Programming Language :: Python :: 3
Classifier: License :: OSI Approved :: MIT License
Requires-Python: >=3.6
License-File: LICENSE
Requires-Dist: mates-controller
Requires-Dist: gpiozero
Requires-Dist: lgpio
